{
  "cycle": 60,
  "born": "2026-05-22T01:46:39.981Z",
  "lastActive": "2026-05-29T01:35:00.205Z",
  "lastStatus": "completed",
  "firstWakeIntroComplete": true,
  "firstWakeIntroAt": "2026-05-22T01:46:39.981Z",
  "lastCycleAt": "2026-05-29T01:35:00.738Z",
  "nextCycleTargetAt": "2026-05-29T02:55:27.341Z",
  "skipGuardSig": "91090c0f43e1520680778623dcc93749129ce16f552fc58a6c2bbb59f39316ff",
  "aiRouting": {
    "providers": {
      "opengateway": {
        "successCount": 16,
        "failureCount": 0,
        "rollingFailures": 0,
        "lastSuccessAt": "2026-05-25T12:49:43.352Z",
        "lastFailureAt": null,
        "avgLatencyMs": 35044,
        "weight": 1,
        "demoteUntil": null
      }
    }
  },
  "feeFloor": {
    "weekStartedAt": null,
    "weekStartBalanceWei": "0",
    "lastWeekBoundaryAt": null
  },
  "problemLab": {
    "experiments": []
  },
  "revenueExplorer": {
    "proposals": [],
    "lastRanAt": "2026-05-29T01:35:01.086Z",
    "runHistory": [
      {
        "ts": "2026-05-28T19:45:18.898Z",
        "evaluated": 0,
        "sunset": 0,
        "proposalsAdded": 0,
        "errors": 0
      },
      {
        "ts": "2026-05-28T23:58:00.488Z",
        "evaluated": 0,
        "sunset": 0,
        "proposalsAdded": 0,
        "errors": 0
      },
      {
        "ts": "2026-05-29T01:35:01.086Z",
        "evaluated": 0,
        "sunset": 0,
        "proposalsAdded": 0,
        "errors": 0
      }
    ],
    "draftProposals": [],
    "rejectedDrafts": []
  }
}
